model_utils/__init__.py
model_utils/choices.py
model_utils/fields.py
model_utils/managers.py
model_utils/models.py
model_utils/py.typed
model_utils/tracker.py
model_utils/locale/cs/LC_MESSAGES/django.mo
model_utils/locale/cs/LC_MESSAGES/django.po
model_utils/locale/de/LC_MESSAGES/django.mo
model_utils/locale/de/LC_MESSAGES/django.po
model_utils/locale/es/LC_MESSAGES/django.mo
model_utils/locale/es/LC_MESSAGES/django.po
model_utils/locale/fa/LC_MESSAGES/django.mo
model_utils/locale/fa/LC_MESSAGES/django.po
model_utils/locale/fr/LC_MESSAGES/django.mo
model_utils/locale/fr/LC_MESSAGES/django.po
model_utils/locale/pt_BR/LC_MESSAGES/django.mo
model_utils/locale/pt_BR/LC_MESSAGES/django.po
model_utils/locale/ru/LC_MESSAGES/django.mo
model_utils/locale/ru/LC_MESSAGES/django.po
model_utils/locale/sv/LC_MESSAGES/django.mo
model_utils/locale/sv/LC_MESSAGES/django.po
model_utils/locale/zh_Hans/LC_MESSAGES/django.mo
model_utils/locale/zh_Hans/LC_MESSAGES/django.po
django_model_utils-4.5.1.dist-info/AUTHORS.rst
django_model_utils-4.5.1.dist-info/LICENSE.txt
django_model_utils-4.5.1.dist-info/METADATA
django_model_utils-4.5.1.dist-info/WHEEL
django_model_utils-4.5.1.dist-info/top_level.txt
django_model_utils-4.5.1.dist-info/RECORD
